Metadata-Version: 2.1
Name: zainy1453-distributions
Version: 0.1
Summary: Gaussian distributions
Home-page: UNKNOWN
Author: Mohamad AlZainy
Author-email: zainy1453@gmail.com
License: UNKNOWN
Platform: UNKNOWN
